HISTORY.rst
LICENSE
MANIFEST.in
Makefile
README.rst
setup.cfg
setup.py
tox.ini
Flask_Simon.egg-info/PKG-INFO
Flask_Simon.egg-info/SOURCES.txt
Flask_Simon.egg-info/dependency_links.txt
Flask_Simon.egg-info/requires.txt
Flask_Simon.egg-info/top_level.txt
docs/Makefile
docs/conf.py
docs/index.rst
docs/make.bat
docs/_themes/flask_theme_support.py
docs/_themes/flask_small/layout.html
docs/_themes/flask_small/theme.conf
docs/_themes/flask_small/static/flasky.css_t
examples/README.rst
examples/flask-login/login.py
examples/flask-login/requirements.txt
examples/flask-login/templates/index.html
examples/flask-login/templates/login.html
examples/flaskr/flaskr.py
examples/flaskr/requirements.txt
examples/flaskr/static/style.css
examples/flaskr/templates/layout.html
examples/flaskr/templates/login.html
examples/flaskr/templates/show_entries.html
flask_simon/__init__.py
tests/__init__.py
tests/requirements.txt
tests/test_simon.py