Metadata-Version: 1.1
Name: Flask-Simon
Version: 0.3.0
Summary: Simple MongoDB Models for Flask
Home-page: https://github.com/dirn/Flask-Simon
Author: Andy Dirnberger
Author-email: dirn@dirnonline.com
License: Copyright (c) 2013, Andy Dirnberger
